pyJSL/RSAhandler.py
pyJSL/__init__.py
pyJSLclient/RSAhandler.py
pyJSLclient/__init__.py
pyJSLclient-0.0.2.dist-info/LICENSE
pyJSLclient-0.0.2.dist-info/METADATA
pyJSLclient-0.0.2.dist-info/WHEEL
pyJSLclient-0.0.2.dist-info/top_level.txt
pyJSLclient-0.0.2.dist-info/RECORD
