Metadata-Version: 2.1
Name: pyJSLclient
Version: 0.0.2
Summary: It makes your WebSocket communications secure.
Home-page: https://github.com/2runo/JSLclient-py
Author: 2runo
Author-email: 2runo04@gmail.com
License: UNKNOWN
Platform: UNKNOWN
Classifier: License :: OSI Approved :: MIT License
Requires-Dist: crypto
Requires-Dist: pycrypto
Requires-Dist: websocket
Requires-Dist: pyopenssl
Requires-Dist: RSAhandler
